make87/__init__.py
make87/config.py
make87/host.py
make87/storage.py
make87/encodings/__init__.py
make87/encodings/base.py
make87/encodings/json_.py
make87/encodings/yaml_.py
make87/encodings/protobuf/__init__.py
make87/encodings/protobuf/pb4.py
make87/encodings/protobuf/pb5.py
make87/encodings/protobuf/pb6.py
make87/interfaces/__init__.py
make87/interfaces/base.py
make87/interfaces/rerun/__init__.py
make87/interfaces/rerun/interface.py
make87/interfaces/rerun/model.py
make87/interfaces/zenoh/__init__.py
make87/interfaces/zenoh/interface.py
make87/interfaces/zenoh/model.py
make87/internal/__init__.py
make87/internal/models/__init__.py
make87/internal/models/application_env_config.py
make87/models/__init__.py
make87/peripherals/__init__.py
make87/peripherals/base.py
make87/peripherals/factory.py
make87/peripherals/manager.py
make87/peripherals/camera/__init__.py
make87/peripherals/codec/__init__.py
make87/peripherals/generic_device/__init__.py
make87/peripherals/gpio/__init__.py
make87/peripherals/gpu/__init__.py
make87/peripherals/i2c/__init__.py
make87/peripherals/isp/__init__.py
make87/peripherals/other/__init__.py
make87/peripherals/real_sense/__init__.py
make87/peripherals/rendering/__init__.py
make87-0.2.2.dist-info/licenses/LICENSE
make87-0.2.2.dist-info/METADATA
make87-0.2.2.dist-info/WHEEL
make87-0.2.2.dist-info/top_level.txt
make87-0.2.2.dist-info/RECORD
